[{"model": "loty2.captain", "pk": 1, "fields": {"name": "Jan1", "surname": "Abcde1"}},{"model": "loty2.captain", "pk": 2, "fields": {"name": "Jan2", "surname": "Abcde2"}},{"model": "loty2.captain", "pk": 3, "fields": {"name": "Jan3", "surname": "Abcde3"}},{"model": "loty2.captain", "pk": 4, "fields": {"name": "Jan4", "surname": "Abcde4"}},{"model": "loty2.captain", "pk": 5, "fields": {"name": "Jan5", "surname": "Abcde5"}},{"model": "loty2.captain", "pk": 6, "fields": {"name": "Jan6", "surname": "Abcde6"}},{"model": "loty2.captain", "pk": 7, "fields": {"name": "Jan7", "surname": "Abcde7"}},{"model": "loty2.captain", "pk": 8, "fields": {"name": "Jan8", "surname": "Abcde8"}},{"model": "loty2.captain", "pk": 9, "fields": {"name": "Jan9", "surname": "Abcde9"}},{"model": "loty2.captain", "pk": 10, "fields": {"name": "Jan10", "surname": "Abcde10"}}]